RonAOVTool/__init__.py
ronaovtool-0.1.4.dist-info/licenses/LICENSE
ronaovtool-0.1.4.dist-info/METADATA
ronaovtool-0.1.4.dist-info/WHEEL
ronaovtool-0.1.4.dist-info/top_level.txt
ronaovtool-0.1.4.dist-info/RECORD
